{"cameraMode":{"drawMode":0,"name":"Shaded","section":"Shading Mode"},"sceneLighting":true,"audioPlay":false,"sceneViewState":{"m_AlwaysRefresh":false,"showFog":true,"showSkybox":true,"showFlares":true,"showImageEffects":true,"showParticleSystems":true,"showVisualEffectGraphs":true,"m_FxEnabled":true},"in2DMode":false,"pivot":{"x":-5.044055461883545,"y":4.135058879852295,"z":-1.7550182342529297},"rotation":{"x":0.08172202855348587,"y":0.6256075501441956,"z":-0.06611676514148712,"w":0.7730507254600525},"size":2.4861717224121095,"orthographic":false}